haruhi/__init__.py
haruhi/pyplot/__init__.py
haruhi/pyplot/mollweide.py
haruhi-1.0.3.dist-info/METADATA
haruhi-1.0.3.dist-info/WHEEL
haruhi-1.0.3.dist-info/top_level.txt
haruhi-1.0.3.dist-info/RECORD
